setup.py
tests/__init__.py
tests/test_main_api.py
wordgraph/__init__.py
wordgraph/analysers.py
wordgraph/describer.py
wordgraph/grapher.py
wordgraph/points.py
wordgraph.egg-info/PKG-INFO
wordgraph.egg-info/SOURCES.txt
wordgraph.egg-info/dependency_links.txt
wordgraph.egg-info/requires.txt
wordgraph.egg-info/top_level.txt
wordgraph/realiser/__init__.py
wordgraph/realiser/english_smart.py
wordgraph/realiser/realiser.py
wordgraph/realiser/templates/en/long/desc.txt
wordgraph/realiser/templates/en/long/linear-series.txt
wordgraph/realiser/templates/en/long/normal-series.txt
wordgraph/realiser/templates/en/long/random-series.txt
wordgraph/realiser/templates/en/long/single-point-series.txt
wordgraph/realiser/templates/en/long/single-point.txt