Metadata-Version: 1.1
Name: wordgraph
Version: 0.0.3
Summary: Produce a natural language description of graphs or data series
Home-page: https://github.com/tleeuwenburg/wordgraph/blob/master/README.md
Author: Tennessee Leeuwenburg
Author-email: tleeuwenburg@gmail.com
License: Apache2
Keywords: python3
Platform: UNKNOWN
Classifier: Development Status :: 3 - Alpha
Classifier: Intended Audience :: Developers
Classifier: Programming Language :: Python :: 3
Classifier: Topic :: Software Development
Classifier: License :: OSI Approved :: Apache Software License
